ntfsutils-stubs/__init__.pyi
ntfsutils-stubs/fs.pyi
ntfsutils-stubs/hardlink.pyi
ntfsutils-stubs/junction.pyi
types_ntfsutils-0.1.5.dist-info/LICENSE
types_ntfsutils-0.1.5.dist-info/METADATA
types_ntfsutils-0.1.5.dist-info/WHEEL
types_ntfsutils-0.1.5.dist-info/RECORD
