Metadata-Version: 2.1
Name: types-ntfsutils
Version: 0.1.5
Summary: Type annotations for `ntfsutils` package
Author: Evgeniy A. Cymbalyuk
Author-email: cimbaluk@gmail.com
Requires-Python: >=3.8
Classifier: Programming Language :: Python :: 3
Classifier: Programming Language :: Python :: 3.8
Classifier: Programming Language :: Python :: 3.9
Classifier: Programming Language :: Python :: 3.10
Classifier: Programming Language :: Python :: 3.11
Classifier: Programming Language :: Python :: 3.12
